CCSocketBianchengJiaocheng1TianWanzhuanSocketTongxinJishu/README.md
CCSocketBianchengJiaocheng1TianWanzhuanSocketTongxinJishu/__init__.py
CCSocketBianchengJiaocheng1TianWanzhuanSocketTongxinJishu/__main__.py
CCSocketBianchengJiaocheng1TianWanzhuanSocketTongxinJishu/file.epub
CCSocketBianchengJiaocheng1TianWanzhuanSocketTongxinJishu/index.html
CCSocketBianchengJiaocheng1TianWanzhuanSocketTongxinJishu/css/__init__.py
CCSocketBianchengJiaocheng1TianWanzhuanSocketTongxinJishu/css/annotations.css
CCSocketBianchengJiaocheng1TianWanzhuanSocketTongxinJishu/css/main.css
CCSocketBianchengJiaocheng1TianWanzhuanSocketTongxinJishu/css/normalize.css
CCSocketBianchengJiaocheng1TianWanzhuanSocketTongxinJishu/css/popup.css
CCSocketBianchengJiaocheng1TianWanzhuanSocketTongxinJishu/font/__init__.py
CCSocketBianchengJiaocheng1TianWanzhuanSocketTongxinJishu/font/fontello.eot
CCSocketBianchengJiaocheng1TianWanzhuanSocketTongxinJishu/font/fontello.svg
CCSocketBianchengJiaocheng1TianWanzhuanSocketTongxinJishu/font/fontello.ttf
CCSocketBianchengJiaocheng1TianWanzhuanSocketTongxinJishu/font/fontello.woff
CCSocketBianchengJiaocheng1TianWanzhuanSocketTongxinJishu/img/__init__.py
CCSocketBianchengJiaocheng1TianWanzhuanSocketTongxinJishu/img/annotator-glyph-sprite.png
CCSocketBianchengJiaocheng1TianWanzhuanSocketTongxinJishu/img/annotator-icon-sprite.png
CCSocketBianchengJiaocheng1TianWanzhuanSocketTongxinJishu/img/apple-touch-icon.png
CCSocketBianchengJiaocheng1TianWanzhuanSocketTongxinJishu/img/cancelfullscreen.png
CCSocketBianchengJiaocheng1TianWanzhuanSocketTongxinJishu/img/close.png
CCSocketBianchengJiaocheng1TianWanzhuanSocketTongxinJishu/img/fullscreen.png
CCSocketBianchengJiaocheng1TianWanzhuanSocketTongxinJishu/img/loader.gif
CCSocketBianchengJiaocheng1TianWanzhuanSocketTongxinJishu/img/menu-icon.png
CCSocketBianchengJiaocheng1TianWanzhuanSocketTongxinJishu/img/save.png
CCSocketBianchengJiaocheng1TianWanzhuanSocketTongxinJishu/img/saved.png
c_c_socket_biancheng_jiaocheng_1_tian_wanzhuan_socket_tongxin_jishu-2024.3.2.0.dist-info/METADATA
c_c_socket_biancheng_jiaocheng_1_tian_wanzhuan_socket_tongxin_jishu-2024.3.2.0.dist-info/WHEEL
c_c_socket_biancheng_jiaocheng_1_tian_wanzhuan_socket_tongxin_jishu-2024.3.2.0.dist-info/entry_points.txt
c_c_socket_biancheng_jiaocheng_1_tian_wanzhuan_socket_tongxin_jishu-2024.3.2.0.dist-info/top_level.txt
c_c_socket_biancheng_jiaocheng_1_tian_wanzhuan_socket_tongxin_jishu-2024.3.2.0.dist-info/RECORD
